#include "opcodes.h"

char *opcodenames[] = {
/* 0x00 */	"nop",
/* 0x01 */	"aconst_null"
/* 0x02 */	"iconst_m1",
/* 0x03 */	"iconst_0",
/* 0x04 */	"iconst_1",
/* 0x05 */	"iconst_2",
/* 0x06 */	"iconst_3",
/* 0x07 */	"iconst_4",
/* 0x08 */	"iconst_5",
/* 0x09 */	"not implemented",
/* 0x0a */	"not implemented",
/* 0x0b */	"not implemented",
/* 0x0c */	"not implemented",
/* 0x0d */	"not implemented",
/* 0x0e */	"not implemented",
/* 0x0f */	"not implemented",
/* 0x10 */	"not implemented",
/* 0x11 */	"not implemented",
/* 0x12 */	"ldc",
/* 0x13 */	"not implemented",
/* 0x14 */	"not implemented",
/* 0x15 */	"iload",
/* 0x16 */	"not implemented",
/* 0x17 */	"not implemented",
/* 0x18 */	"not implemented",
/* 0x19 */	"not implemented",
/* 0x1a */	"iload_0",
/* 0x1b */	"iload_1",
/* 0x1c */	"iload_2",
/* 0x1d */	"iload_3",
/* 0x1e */	"not implemented",
/* 0x1f */	"not implemented",
/* 0x20 */	"not implemented",
/* 0x21 */	"not implemented",
/* 0x22 */	"not implemented",
/* 0x23 */	"not implemented",
/* 0x24 */	"not implemented",
/* 0x25 */	"not implemented",
/* 0x26 */	"not implemented",
/* 0x27 */	"not implemented",
/* 0x28 */	"not implemented",
/* 0x29 */	"not implemented",
/* 0x2a */	"aload_0",
/* 0x2b */	"aload_1",
/* 0x2c */	"aload_2",
/* 0x2d */	"aload_3",
/* 0x2e */	"not implemented",
/* 0x2f */	"not implemented",
/* 0x30 */	"not implemented",
/* 0x31 */	"not implemented",
/* 0x32 */	"not implemented",
/* 0x33 */	"not implemented",
/* 0x34 */	"not implemented",
/* 0x45 */	"not implemented",
/* 0x36 */	"istore",
/* 0x37 */	"not implemented",
/* 0x38 */	"not implemented",
/* 0x39 */	"not implemented",
/* 0x3a */	"astore",
/* 0x3b */	"istore_0",
/* 0x3c */	"istore_1",
/* 0x3d */	"istore_2",
/* 0x3e */	"istore_3",
/* 0x3f */	"not implemented",
/* 0x40 */	"not implemented",
/* 0x41 */	"not implemented",
/* 0x42 */	"not implemented",
/* 0x43 */	"not implemented",
/* 0x44 */	"not implemented",
/* 0x45 */	"not implemented",
/* 0x46 */	"not implemented",
/* 0x47 */	"not implemented",
/* 0x48 */	"not implemented",
/* 0x49 */	"not implemented",
/* 0x4a */	"not implemented",
/* 0x4b */	"astore_0",
/* 0x4c */	"astore_1",
/* 0x4d */	"astore_2",
/* 0x4e */	"astore_3",
/* 0x4f */	"not implemented",
/* 0x50 */	"not implemented",
/* 0x51 */	"not implemented",
/* 0x52 */	"not implemented",
/* 0x53 */	"not implemented",
/* 0x54 */	"not implemented",
/* 0x55 */	"not implemented",
/* 0x56 */	"not implemented",
/* 0x57 */	"not implemented",
/* 0x58 */	"not implemented",
/* 0x59 */	"dup",
/* 0x5a */	"not implemented",
/* 0x5b */	"not implemented",
/* 0x5c */	"not implemented",
/* 0x5d */	"not implemented",
/* 0x5e */	"not implemented",
/* 0x5f */	"not implemented",
/* 0x60 */	"not implemented",
/* 0x61 */	"not implemented",
/* 0x62 */	"not implemented",
/* 0x63 */	"not implemented",
/* 0x64 */	"not implemented",
/* 0x65 */	"not implemented",
/* 0x66 */	"not implemented",
/* 0x67 */	"not implemented",
/* 0x68 */	"not implemented",
/* 0x69 */	"not implemented",
/* 0x6a */	"not implemented",
/* 0x6b */	"not implemented",
/* 0x6c */	"not implemented",
/* 0x6d */	"not implemented",
/* 0x6e */	"not implemented",
/* 0x6f */	"not implemented",
/* 0x70 */	"not implemented",
/* 0x71 */	"not implemented",
/* 0x72 */	"not implemented",
/* 0x73 */	"not implemented",
/* 0x74 */	"not implemented",
/* 0x75 */	"not implemented",
/* 0x76 */	"not implemented",
/* 0x77 */	"not implemented",
/* 0x78 */	"not implemented",
/* 0x79 */	"not implemented",
/* 0x7a */	"not implemented",
/* 0x7b */	"not implemented",
/* 0x7c */	"not implemented",
/* 0x7d */	"not implemented",
/* 0x7e */	"not implemented",
/* 0x7f */	"not implemented",
/* 0x80 */	"not implemented",
/* 0x81 */	"not implemented",
/* 0x82 */	"not implemented",
/* 0x83 */	"not implemented",
/* 0x84 */	"not implemented",
/* 0x85 */	"not implemented",
/* 0x86 */	"not implemented",
/* 0x87 */	"not implemented",
/* 0x88 */	"not implemented",
/* 0x89 */	"not implemented",
/* 0x8a */	"not implemented",
/* 0x8b */	"not implemented",
/* 0x8c */	"not implemented",
/* 0x8d */	"not implemented",
/* 0x8e */	"not implemented",
/* 0x8f */	"not implemented",
/* 0x90 */	"not implemented",
/* 0x91 */	"not implemented",
/* 0x92 */	"not implemented",
/* 0x93 */	"not implemented",
/* 0x94 */	"not implemented",
/* 0x95 */	"not implemented",
/* 0x96 */	"not implemented",
/* 0x97 */	"not implemented",
/* 0x98 */	"not implemented",
/* 0x99 */	"not implemented",
/* 0x9a */	"not implemented",
/* 0x9b */	"not implemented",
/* 0x9c */	"not implemented",
/* 0x9d */	"not implemented",
/* 0x9e */	"not implemented",
/* 0x9f */	"not implemented",
/* 0xa0 */	"not implemented",
/* 0xa1 */	"not implemented",
/* 0xa2 */	"not implemented",
/* 0xa3 */	"not implemented",
/* 0xa4 */	"not implemented",
/* 0xa5 */	"not implemented",
/* 0xa6 */	"not implemented",
/* 0xa7 */	"goto",
/* 0xa8 */	"not implemented",
/* 0xa9 */	"not implemented",
/* 0xaa */	"not implemented",
/* 0xab */	"not implemented",
/* 0xac */	"ireturn",
/* 0xad */	"not implemented",
/* 0xae */	"not implemented",
/* 0xaf */	"not implemented",
/* 0xb0 */	"not implemented",
/* 0xb1 */	"return",
/* 0xb2 */	"getstatic",
/* 0xb3 */	"not implemented",
/* 0xb4 */	"not implemented",
/* 0xb5 */	"not implemented",
/* 0xb6 */	"invokevirtual",
/* 0xb7 */	"invokespecial",
/* 0xb8 */	"invokestatic",
/* 0xb9 */	"not implemented",
/* 0xba */	"not implemented",
/* 0xbb */	"new"
/* 0xbc */	"not implemented",
/* 0xbd */	"not implemented",
/* 0xbe */	"not implemented",
/* 0xbf */	"not implemented",
/* 0xc0 */	"not implemented",
/* 0xc1 */	"not implemented",
/* 0xc2 */	"not implemented",
/* 0xc3 */	"not implemented",
/* 0xc4 */	"not implemented",
/* 0xc5 */	"not implemented",
/* 0xc6 */	"not implemented",
/* 0xc7 */	"not implemented",
/* 0xc8 */	"not implemented",
/* 0xc9 */	"not implemented",
/* 0xca */	"not implemented",
/* 0xcb */	"not implemented",
/* 0xcc */	"not implemented",
/* 0xcd */	"not implemented",
/* 0xce */	"not implemented",
/* 0xcf */	"not implemented",
/* 0xd0 */	"not implemented",
/* 0xd1 */	"not implemented",
/* 0xd2 */	"not implemented",
/* 0xd3 */	"not implemented",
/* 0xd4 */	"not implemented",
/* 0xd5 */	"not implemented",
/* 0xd6 */	"not implemented",
/* 0xd7 */	"not implemented",
/* 0xd8 */	"not implemented",
/* 0xd9 */	"not implemented",
/* 0xda */	"not implemented",
/* 0xdb */	"not implemented",
/* 0xdc */	"not implemented",
/* 0xdd */	"not implemented",
/* 0xde */	"not implemented",
/* 0xdf */	"not implemented",
/* 0xe0 */	"not implemented",
/* 0xe1 */	"not implemented",
/* 0xe2 */	"not implemented",
/* 0xe3 */	"not implemented",
/* 0xe4 */	"not implemented",
/* 0xe5 */	"not implemented",
/* 0xe6 */	"not implemented",
/* 0xe7 */	"not implemented",
/* 0xe8 */	"not implemented",
/* 0xe9 */	"not implemented",
/* 0xea */	"not implemented",
/* 0xeb */	"not implemented",
/* 0xec */	"not implemented",
/* 0xed */	"not implemented",
/* 0xee */	"not implemented",
/* 0xef */	"not implemented",
/* 0xf0 */	"not implemented",
/* 0xf1 */	"not implemented",
/* 0xf2 */	"not implemented",
/* 0xf3 */	"not implemented",
/* 0xf4 */	"not implemented",
/* 0xf5 */	"not implemented",
/* 0xf6 */	"not implemented",
/* 0xf7 */	"not implemented",
/* 0xf8 */	"not implemented",
/* 0xf9 */	"not implemented",
/* 0xfa */	"not implemented",
/* 0xfb */	"not implemented",
/* 0xfc */	"not implemented",
/* 0xfd */	"not implemented",
/* 0xfe */	"not implemented",
/* 0xff */	"not implemented",
};
